{
  "$schema": "http://json-schema.org/draft-07/schema#",
  "title": "ExecuteMsg",
  "oneOf": [
    {
      "type": "object",
      "required": [
        "donate"
      ],
      "properties": {
        "donate": {
          "type": "object",
          "additionalProperties": false
        }
      },
      "additionalProperties": false
    },
    {
      "type": "object",
      "required": [
        "withdraw"
      ],
      "properties": {
        "withdraw": {
          "type": "object",
          "additionalProperties": false
        }
      },
      "additionalProperties": false
    }
  ]
}
